{
  "2063R3": 57,
  "65CXVm": 32,
  "8PX9Yx": 32,
  "1di0B1": 33,
  "A5u6CE": 20,
  "13jkRV": 20,
  "4X23kE": 64,
  "AwDQxx": 73,
  "D6lO16": 53,
  "BrkiXj": 20,
  "DeAdOp": 54,
  "CIrGnS": 29,
  "6CzUfc": 29,
  "FtgoLq": 33,
  "8IZDot": 36,
  "H2uEVZ": 43,
  "5k8xTs": 60,
  "6uqdfR": 50,
  "9iRIcF": 50,
  "1qZ7LC": 12,
  "F827sZ": 61,
  "IJkp1Q": 32,
  "8lfTuo": 88,
  "HOsm3i": 53,
  "LwAYi7": 36,
  "MdMT5s": 36,
  "C0CuJd": 106,
  "U8goJB": 27,
  "TiPHTE": 20,
  "Ub7pn2": 21,
  "TsrB5K": 54,
  "Puickf": 36,
  "OMnrtI": 20,
  "SHcF9d": 43,
  "W9hpGT": 20,
  "HBrs5p": 88,
  "WrJFM7": 20,
  "UVUNH6": 31,
  "KuaIuW": 88,
  "VpJTqd": 44,
  "c7HCQ7": 23,
  "bL748U": 53,
  "YNjkBe": 20,
  "TQQ9bT": 50,
  "ceWf08": 35,
  "VgLqGN": 20,
  "gD2v6u": 43,
  "WDbIqO": 36,
  "jLwszn": 98,
  "lZj50n": 54,
  "Wwwhs3": 20,
  "m2pL6i": 27,
  "kKiPXQ": 20,
  "YzIC3T": 36,
  "s48P2Z": 54,
  "ZgU6RE": 36,
  "pvKQvR": 20,
  "aBjrB3": 36,
  "ajYcGf": 45,
  "tMd2Ny": 43,
  "uZKQPj": 69,
  "rZ8NCv": 55,
  "w7YksW": 11,
  "i3rlMH": 60,
  "sBlZOh": 54,
  "yPpoOG": 54,
  "tVafyE": 20,
  "1TVpT6": 46,
  "6SPcBa": 50,
  "57vGzz": 74,
  "80zbf1": 36,
  "tNXzuD": 96,
  "kF4x1U": 37,
  "HtTIBT": 28,
  "WCw4EK": 20,
  "Fy5jk7": 69,
  "z91QcD": 36,
  "JPe46p": 54,
  "yx5GyH": 50,
  "r6hLj4": 32,
  "pFDGrd": 51,
  "v5ueNg": 30,
  "uaPAjg": 51,
  "xEJ6mv": 20,
  "w4gAvJ": 88
}
